<?xml version="1.0"?>
<!DOCTYPE feature SYSTEM "gdb-target.dtd">
<feature name="org.gnu.gdb.riscv.csr">
	<!-- Regnum for CSR is (csr_regno + 65), used by remote protocol -->
	<!-- M-mode Information -->
	<!-- <reg name="mvendorid"    bitsize="64" regnum="0xf52" type="int"/> -->
	<reg name="marchid"      bitsize="64" regnum="0xf53" type="int"/>
	<reg name="mimpid"       bitsize="64" regnum="0xf54" type="int"/>
	<reg name="mhartid"      bitsize="64" regnum="0xf55" type="int"/>
	<!-- <reg name="mconfigptr"   bitsize="64" regnum="0xf56" type="int"/> -->
	<!-- M-mode Exception Setting -->
	<reg name="mstatus"       bitsize="64" regnum="0x341" type="int"/>
	<reg name="misa"          bitsize="64" regnum="0x342" type="int"/>
	<reg name="medeleg"       bitsize="64" regnum="0x343" type="int"/>
	<reg name="mideleg"       bitsize="64" regnum="0x344" type="int"/>
	<reg name="mie"           bitsize="64" regnum="0x345" type="int"/>
	<reg name="mtvec"         bitsize="64" regnum="0x346" type="int"/>
	<reg name="mcounteren"    bitsize="64" regnum="0x347" type="int"/>
	<!-- M-mode Exception Handling -->
	<reg name="mscratch"     bitsize="64" regnum="0x381" type="int"/>
	<reg name="mepc"         bitsize="64" regnum="0x382" type="int"/>
	<reg name="mcause"       bitsize="64" regnum="0x383" type="int"/>
	<reg name="mtval"        bitsize="64" regnum="0x384" type="int"/>
	<reg name="mip"          bitsize="64" regnum="0x385" type="int"/>
	<!-- M-mode Counter -->
	<reg name="mcycle"        bitsize="64" regnum="0xb41" type="int"/>
	<reg name="minstret"      bitsize="64" regnum="0xb43" type="int"/>
	<!-- U-mode Counter -->
	<reg name="cycle"        bitsize="64" regnum="0xc41" type="int"/>
	<reg name="time"          bitsize="64" regnum="0xc42" type="int"/>
	<reg name="instret"      bitsize="64" regnum="0xc43" type="int"/>
	<!-- M-mode CPU TYPE. -->
	<!-- <reg name="mcpuid"   bitsize="64" regnum="0x1001" type="int"/> -->
	<!-- <reg name="mapbaddr"   bitsize="64" regnum="0x1002" type="int"/> -->
</feature>
